anomaly_detection/__init__.py
anomaly_detection/anomaly_detect_ts.py
anomaly_detection/anomaly_detect_vec.py
anomaly_detection/dynamic_cusum.py
streaming_anomaly_detection-0.0.9.dist-info/LICENSE
streaming_anomaly_detection-0.0.9.dist-info/METADATA
streaming_anomaly_detection-0.0.9.dist-info/WHEEL
streaming_anomaly_detection-0.0.9.dist-info/top_level.txt
streaming_anomaly_detection-0.0.9.dist-info/RECORD
