Metadata-Version: 2.1
Name: streaming-anomaly-detection
Version: 0.0.9
Summary: A pure python implementation of https://github.com/twitter/AnomalyDetection
Home-page: UNKNOWN
Author: UNKNOWN
Author-email: UNKNOWN
License: UNKNOWN
Platform: UNKNOWN
Requires-Dist: scipy (>=1.2.0)
Requires-Dist: pandas (>=1.3.0)
Requires-Dist: dask (>=2.9.0)
Requires-Dist: distributed (==2.21.0)
Requires-Dist: toolz (==0.10.0)
Requires-Dist: cloudpickle (==1.6.0)
Requires-Dist: statsmodels (>=0.13.2)
Requires-Dist: asn1crypto
